AUTHORS.rst
CONTRIBUTING.rst
HISTORY.rst
LICENSE
MANIFEST.in
README.md
setup.cfg
setup.py
deathray/__init__.py
deathray/cli.py
deathray.egg-info/PKG-INFO
deathray.egg-info/SOURCES.txt
deathray.egg-info/dependency_links.txt
deathray.egg-info/entry_points.txt
deathray.egg-info/not-zip-safe
deathray.egg-info/requires.txt
deathray.egg-info/top_level.txt
docs/authors.rst
docs/conf.py
docs/contributing.rst
docs/history.rst
docs/index.rst
docs/installation.rst
docs/readme.rst
docs/usage.rst
tests/__init__.py
tests/test_deathray.py