Metadata-Version: 1.2
Name: deathray
Version: 0.1.0
Summary: Anomaly Detection in an Astrophysics Simulation
Home-page: https://github.com/yngtodd/deathray
Author: Drew Schmidt and Todd Young
Author-email: youngmt1@ornl.gov
License: MIT license
Keywords: deathray
Platform: UNKNOWN
Classifier: Development Status :: 2 - Pre-Alpha
Classifier: Intended Audience :: Developers
Classifier: License :: OSI Approved :: MIT License
Classifier: Natural Language :: English
Classifier: Programming Language :: Python :: 3.6
Classifier: Programming Language :: Python :: 3.7
Classifier: Programming Language :: Python :: 3.8
Requires-Python: >=3.5
